deatool/__init__.py
deatool/deasolver.py
deatool/MMODEL/CCR.py
deatool/MMODEL/CCR_pyomo.py
deatool/MMODEL/DDF.py
deatool/MMODEL/DDF_pyomo.py
deatool/MMODEL/SBM.py
deatool/MMODEL/SBM_pyomo.py
deatool/MMODEL/__init__.py
deatool/QT5/Ui_table.py
deatool/QT5/__init__.py
deatool/scrips/__init__.py
deatool/scrips/run.py
deatool-1.1.7.dist-info/METADATA
deatool-1.1.7.dist-info/WHEEL
deatool-1.1.7.dist-info/top_level.txt
deatool-1.1.7.dist-info/RECORD
