Metadata-Version: 2.1
Name: deatool
Version: 1.1.7
Summary: Data envelopment analysis efficiency calculator
Home-page: https://github.com/DEATien
Author: WANGY
Author-email: wangy_prince@126.com
License: UNKNOWN
Platform: UNKNOWN
Requires-Python: <3.10
Requires-Dist: pandas
Requires-Dist: PyQt5
Requires-Dist: numpy
Requires-Dist: PyQt5-tools
Requires-Dist: openpyxl
Requires-Dist: pyomo
Requires-Dist: gurobipy
